[
  {
    "name": "Dante and Virgil in Hell",
    "id": "bouguereau-dante-and-virgil-in-hell-1850",
    "category": "academic"
  },
  {
    "name": "Fraternal Love",
    "id": "bouguereau-fraternal-love-1851",
    "category": "academic"
  },
  {
    "name": "The Bather",
    "id": "bouguereau-bather-1870",
    "category": "academic"
  },
  {
    "name": "Italian Girl Drawing Water",
    "id": "bouguereau-italian-girl-drawing-water-1871",
    "category": "academic"
  },
  {
    "name": "Nymphs and Satyr",
    "id": "bouguereau-nymphs-and-satyr-1873",
    "category": "academic"
  },
  {
    "name": "At the Edge of the Brook (1)",
    "id": "bouguereau-at-the-edge-of-the-brook-1875",
    "category": "academic"
  },
  {
    "name": "At the Edge of the Brook (2)",
    "id": "bouguereau-at-the-edge-of-the-brook-1879",
    "category": "academic"
  },
  {
    "name": "Nymphaeum",
    "id": "bouguereau-nymphaeum-1878",
    "category": "academic"
  },
  {
    "name": "A Young Girl Defending Herself Against Eros",
    "id": "bouguereau-young-girl-defending-herself-against-eros-1880",
    "category": "academic"
  },
  {
    "name": "Flagellation of Our Lord Jesus Christ",
    "id": "bouguereau-flagellation-of-our-lord-jesus-christ-1880",
    "category": "academic"
  },
  {
    "name": "Nut Gatherers",
    "id": "bouguereau-nut-gatherers-1882",
    "category": "academic"
  },
  {
    "name": "Bouguereau Biblis",
    "id": "bouguereau-bouguereau-biblis-1884",
    "category": "academic"
  },
  {
    "name": "Lost Pleiad",
    "id": "bouguereau-lost-pleiad-1884",
    "category": "academic"
  },
  {
    "name": "Woman with Shell",
    "id": "bouguereau-woman-with-shell-1885",
    "category": "academic"
  },
  {
    "name": "Young Girl Going to Fountain",
    "id": "bouguereau-young-girl-going-to-fountain-1885",
    "category": "academic"
  },
  {
    "name": "Thirst",
    "id": "bouguereau-thirst-1886",
    "category": "academic"
  },
  {
    "name": "Bohemian",
    "id": "bouguereau-bohemian-1890",
    "category": "academic"
  },
  {
    "name": "A Private Vocation",
    "id": "bouguereau-private-vacation-1890",
    "category": "academic"
  },
  {
    "name": "Penelope",
    "id": "bouguereau-penelope-1891",
    "category": "academic"
  },
  {
    "name": "Youth",
    "id": "bouguereau-youth-1893",
    "category": "academic"
  },
  {
    "name": "Not too Much to Carry",
    "id": "bouguereau-not-too-much-to-carry-1895",
    "category": "academic"
  },
  {
    "name": "Spring Breeze",
    "id": "bouguereau-spring-breeze-1895",
    "category": "academic"
  },
  {
    "name": "A Calling",
    "id": "bouguereau-calling-1896",
    "category": "academic"
  },
  {
    "name": "Wave",
    "id": "bouguereau-wave-1896",
    "category": "academic"
  },
  {
    "name": "Admiration",
    "id": "bouguereau-admiration-1897",
    "category": "academic"
  },
  {
    "name": "Tricoeause",
    "id": "bouguereau-tricoeause-1897",
    "category": "academic"
  },
  {
    "name": "Head of a Young Girl",
    "id": "bouguereau-head-of-a-young-girl-1898",
    "category": "academic"
  },
  {
    "name": "A Childhood Idyll",
    "id": "bouguereau-childhood-idyll-1900",
    "category": "academic"
  }
]
