[
  {
    "name": "Absinthe Drinkers",
    "id": "degas-absinthe-drinkers-1876",
    "category": "impressionism"
  },
  {
    "name": "Woman with Opera Glasses",
    "id": "degas-woman-with-opera-glasses-1876",
    "category": "impressionism"
  },
  {
    "name": "Café-Concert at Les Ambassadeurs",
    "id": "degas-cafe-concert-at-les-ambassadeurs-1877",
    "category": "impressionism"
  },
  {
    "name": "Dancer with Bouquet",
    "id": "degas-dancer-with-bouquet-1877",
    "category": "impressionism"
  },
  {
    "name": "The Star",
    "id": "degas-star-1877",
    "category": "impressionism"
  },
  {
    "name": "Song of the Dog",
    "id": "degas-song-of-the-dog-1877",
    "category": "impressionism"
  },
  {
    "name": "Singer with a Glove",
    "id": "degas-singer-with-a-glove-1878",
    "category": "impressionism"
  },
  {
    "name": "Dancer with a Fan",
    "id": "degas-dancer-with-a-fan-1879",
    "category": "impressionism"
  },
  {
    "name": "Before the Entrance",
    "id": "degas-before-the-entrance-1880",
    "category": "impressionism"
  },
  {
    "name": "Morning Bath",
    "id": "degas-morning-bath-1883",
    "category": "impressionism"
  },
  {
    "name": "Dancer in Green Tutu",
    "id": "degas-dancer-in-green-tutu-1885",
    "category": "impressionism"
  },
  {
    "name": "The Tub",
    "id": "degas-tub-1886",
    "category": "impressionism"
  },
  {
    "name": "Woman Drying Herself",
    "id": "degas-woman-drying-herself-1886",
    "category": "impressionism"
  },
  {
    "name": "Race Horses",
    "id": "degas-race-horses-1888",
    "category": "impressionism"
  },
  {
    "name": "Woman Having Her Hair Combed",
    "id": "degas-woman-having-her-hair-combed-1888",
    "category": "impressionism"
  },
  {
    "name": "Seated Woman Combing Her Hair",
    "id": "degas-seated-woman-combing-her-hair-1890",
    "category": "impressionism"
  },
  {
    "name": "The Morning Bath",
    "id": "degas-morning-bath-1890",
    "category": "impressionism"
  },
  {
    "name": "After the Bath",
    "id": "degas-after-the-bath-1894",
    "category": "impressionism"
  },
  {
    "name": "Ballet Dancers in the Wings",
    "id": "degas-ballet-dancers-in-the-wings-1895",
    "category": "impressionism"
  },
  {
    "name": "Two Bathers on the Grass",
    "id": "degas-bathers-on-the-grass-1895",
    "category": "impressionism"
  }
]
